<annotation>
  <folder>VOC2007</folder>
  <filename>1702d35a0_0.png</filename>
  <source>
    <database>Kaggle Rainforest Connection Species Audio Detection Database</database>
  </source>
  <size>
    <width>387</width>
    <height>154</height>
    <depth>3</depth>
  </size>
  <segmented>0</segmented>
  <object>
    <name>23</name>
    <difficult>0</difficult>
    <bndbox>
      <xmin>291.6254625</xmin>
      <ymin>6.6586688305763175</ymin>
      <xmax>353.75508750000006</xmax>
      <ymax>15.819988811601746</ymax>
    </bndbox>
  </object>
</annotation>
