<annotation>
  <folder>VOC2007</folder>
  <filename>2717a930e_0.png</filename>
  <source>
    <database>Kaggle Rainforest Connection Species Audio Detection Database</database>
  </source>
  <size>
    <width>387</width>
    <height>154</height>
    <depth>3</depth>
  </size>
  <segmented>0</segmented>
  <object>
    <name>9</name>
    <difficult>0</difficult>
    <bndbox>
      <xmin>64.53225</xmin>
      <ymin>40.209660908209514</ymin>
      <xmax>224.0810625</xmax>
      <ymax>54.60134473972114</ymax>
    </bndbox>
  </object>
</annotation>
