<annotation>
  <folder>VOC2007</folder>
  <filename>d2cb96229_0.png</filename>
  <source>
    <database>Kaggle Rainforest Connection Species Audio Detection Database</database>
  </source>
  <size>
    <width>387</width>
    <height>154</height>
    <depth>3</depth>
  </size>
  <segmented>0</segmented>
  <object>
    <name>3</name>
    <difficult>0</difficult>
    <bndbox>
      <xmin>43.95110625</xmin>
      <ymin>62.864165841830086</ymin>
      <xmax>112.68230625</xmax>
      <ymax>128.69644571182087</ymax>
    </bndbox>
  </object>
  <object>
    <name>3</name>
    <difficult>0</difficult>
    <bndbox>
      <xmin>106.90439624999998</xmin>
      <ymin>62.864165841830086</ymin>
      <xmax>175.63559624999996</xmax>
      <ymax>128.69644571182087</ymax>
    </bndbox>
  </object>
</annotation>
